paradox/__init__.py
paradox/decoder.py
paradox/encoder.py
paradox/engine.py
paradox/mixer.py
paradox/persistence.py
paradox/simulation.py
paradox/temporal.py
paradox/utils.py
paradox/visualization.py
paradox/autonomous/__init__.py
paradox/autonomous/agent.py
paradox/distributed/__init__.py
paradox/distributed/client.py
paradox/distributed/cluster.py
paradox/distributed/consensus.py
paradox/distributed/edge.py
paradox/distributed/server.py
paradox/distributed/shard.py
paradox/evolution/__init__.py
paradox/evolution/optimizer.py
paradox/media/__init__.py
paradox/media/clip_module.py
paradox/media/image.py
paradox/media/temporal.py
paradox/media/text.py
paradox/media/video.py
paradox/safety/__init__.py
paradox/safety/guard.py
paradox/ui/__init__.py
paradox/ui/dashboard.py
paradoxlf-0.17.0.dist-info/licenses/LICENSE
paradoxlf-0.17.0.dist-info/METADATA
paradoxlf-0.17.0.dist-info/WHEEL
paradoxlf-0.17.0.dist-info/entry_points.txt
paradoxlf-0.17.0.dist-info/top_level.txt
paradoxlf-0.17.0.dist-info/RECORD
