Metadata-Version: 2.4
Name: paradoxlf
Version: 0.17.0
Summary: A latent memory and active inference engine for AI agents.
Author: Ethco Coders
Author-email: contact@ethcocoders.com
Classifier: Programming Language :: Python :: 3
Classifier: License :: OSI Approved :: MIT License
Classifier: Operating System :: OS Independent
Classifier: Topic :: Scientific/Engineering :: Artificial Intelligence
Classifier: Topic :: Scientific/Engineering :: Artificial Intelligence
Classifier: Development Status :: 3 - Alpha
Requires-Python: >=3.7
License-File: LICENSE
Requires-Dist: numpy>=1.20.0
Provides-Extra: ui
Requires-Dist: streamlit; extra == "ui"
Requires-Dist: plotly; extra == "ui"
Provides-Extra: ai
Requires-Dist: sentence-transformers; extra == "ai"
Requires-Dist: torch; extra == "ai"
Requires-Dist: transformers; extra == "ai"
Provides-Extra: server
Requires-Dist: fastapi; extra == "server"
Requires-Dist: uvicorn; extra == "server"
Requires-Dist: requests; extra == "server"
Dynamic: author
Dynamic: author-email
Dynamic: classifier
Dynamic: description
Dynamic: description-content-type
Dynamic: license-file
Dynamic: provides-extra
Dynamic: requires-dist
Dynamic: requires-python
Dynamic: summary
